rev_assets/__init__.py
rev_assets-1.0.3.dist-info/DESCRIPTION.rst
rev_assets-1.0.3.dist-info/METADATA
rev_assets-1.0.3.dist-info/RECORD
rev_assets-1.0.3.dist-info/WHEEL
rev_assets-1.0.3.dist-info/metadata.json
rev_assets-1.0.3.dist-info/top_level.txt
