Metadata-Version: 2.0
Name: rev-assets
Version: 1.0.3
Summary: Make possible to use hashed static assets generated by tools like Gulp or Webpack
Home-page: http://github.com/jpscaletti/rev-assets
Author: Juan-Pablo Scaletti
Author-email: juanpablo@lucumalabs.com
License: BSD-3-Clause (see LICENSE)
Platform: UNKNOWN
Classifier: Development Status :: 5 - Production/Stable
Classifier: Environment :: Web Environment
Classifier: Intended Audience :: Developers
Classifier: License :: OSI Approved :: BSD License
Classifier: Programming Language :: Python :: 2
Classifier: Programming Language :: Python :: 2.7
Classifier: Programming Language :: Python :: 3
Classifier: Programming Language :: Python :: 3.3
Classifier: Programming Language :: Python :: 3.4
Classifier: Programming Language :: Python :: 3.5
Classifier: Programming Language :: Python :: 3.6
